stackit/cdn/__init__.py
stackit/cdn/api/__init__.py
stackit/cdn/api/default_api.py
stackit/cdn/api_client.py
stackit/cdn/api_response.py
stackit/cdn/configuration.py
stackit/cdn/exceptions.py
stackit/cdn/models/__init__.py
stackit/cdn/models/config.py
stackit/cdn/models/config_patch.py
stackit/cdn/models/create_distribution_payload.py
stackit/cdn/models/create_distribution_response.py
stackit/cdn/models/custom_domain.py
stackit/cdn/models/delete_custom_domain_response.py
stackit/cdn/models/delete_distribution_response.py
stackit/cdn/models/distribution.py
stackit/cdn/models/distribution_logs_record.py
stackit/cdn/models/distribution_statistics_record.py
stackit/cdn/models/distribution_statistics_record_entry.py
stackit/cdn/models/distribution_statistics_record_regions.py
stackit/cdn/models/distribution_waf.py
stackit/cdn/models/domain.py
stackit/cdn/models/domain_status.py
stackit/cdn/models/error_details.py
stackit/cdn/models/find_cache_paths_response.py
stackit/cdn/models/find_cache_paths_response_entry.py
stackit/cdn/models/generic_json_response.py
stackit/cdn/models/get_cache_info_response.py
stackit/cdn/models/get_cache_info_response_history_entry.py
stackit/cdn/models/get_custom_domain_custom_certificate.py
stackit/cdn/models/get_custom_domain_managed_certificate.py
stackit/cdn/models/get_custom_domain_response.py
stackit/cdn/models/get_custom_domain_response_certificate.py
stackit/cdn/models/get_distribution_response.py
stackit/cdn/models/get_logs_response.py
stackit/cdn/models/get_logs_search_filters_response.py
stackit/cdn/models/get_statistics_response.py
stackit/cdn/models/http_backend.py
stackit/cdn/models/http_backend_patch.py
stackit/cdn/models/list_distributions_response.py
stackit/cdn/models/list_waf_collections_response.py
stackit/cdn/models/loki_log_sink.py
stackit/cdn/models/optimizer.py
stackit/cdn/models/optimizer_patch.py
stackit/cdn/models/patch_distribution_payload.py
stackit/cdn/models/patch_distribution_response.py
stackit_cdn-1.7.1.dist-info/METADATA
stackit_cdn-1.7.1.dist-info/WHEEL
stackit_cdn-1.7.1.dist-info/licenses/LICENSE.md
stackit_cdn-1.7.1.dist-info/licenses/NOTICE.txt
stackit_cdn-1.7.1.dist-info/RECORD
